[
  {
    "symbol": "XRP-USD",
    "openInterest": "13777.6",
    "markPrice": "1.1457",
    "indexPrice": "1.1465",
    "fundingRate": "0.0000125",
    "nextFundingTime": 1781388000000
  },
  {
    "symbol": "SUI-USD",
    "openInterest": "7839.6",
    "markPrice": "0.7637",
    "indexPrice": "0.764",
    "fundingRate": "0.0000125",
    "nextFundingTime": 1781388000000
  },
  {
    "symbol": "AAPL-USD",
    "openInterest": "10.58",
    "markPrice": "290.63",
    "indexPrice": "290.63",
    "fundingRate": "0.00000625",
    "nextFundingTime": 1781388000000
  },
  {
    "symbol": "WLD-USD",
    "openInterest": "143018",
    "markPrice": "0.5001",
    "indexPrice": "0.5004",
    "fundingRate": "0.0000125",
    "nextFundingTime": 1781388000000
  },
  {
    "symbol": "1000PEPE-USD",
    "openInterest": "150328",
    "markPrice": "0.002846",
    "indexPrice": "0.002846",
    "fundingRate": "0.0000125",
    "nextFundingTime": 1781388000000
  },
  {
    "symbol": "DASH-USD",
    "openInterest": "37.58",
    "markPrice": "35.175",
    "indexPrice": "35.21",
    "fundingRate": "-0.0000001612728513",
    "nextFundingTime": 1781388000000
  },
  {
    "symbol": "XAUT-USD",
    "openInterest": "1199.6366",
    "markPrice": "4226.7",
    "indexPrice": "4225.5",
    "fundingRate": "0.00000625",
    "nextFundingTime": 1781388000000
  },
  {
    "symbol": "AAVE-USD",
    "openInterest": "41.24",
    "markPrice": "66.45",
    "indexPrice": "66.47",
    "fundingRate": "0.0000125",
    "nextFundingTime": 1781388000000
  },
  {
    "symbol": "META-USD",
    "openInterest": "4.956",
    "markPrice": "569.32",
    "indexPrice": "569.32",
    "fundingRate": "0.00000625",
    "nextFundingTime": 1781388000000
  },
  {
    "symbol": "WIF-USD",
    "openInterest": "1896",
    "markPrice": "0.16005",
    "indexPrice": "0.1601",
    "fundingRate": "0.0000125",
    "nextFundingTime": 1781388000000
  },
  {
    "symbol": "TAO-USD",
    "openInterest": "0",
    "markPrice": "255.15",
    "indexPrice": "255.3",
    "fundingRate": "0.0000125",
    "nextFundingTime": 1781388000000
  },
  {
    "symbol": "SOSO-USD",
    "openInterest": "0",
    "markPrice": "0.7269",
    "indexPrice": "0.7269",
    "fundingRate": "0.0000125",
    "nextFundingTime": 1760774400000
  },
  {
    "symbol": "NEAR-USD",
    "openInterest": "2089.2",
    "markPrice": "2.1105",
    "indexPrice": "2.111",
    "fundingRate": "0.0000125",
    "nextFundingTime": 1781388000000
  },
  {
    "symbol": "NATGAS-USD",
    "openInterest": "0",
    "markPrice": "3.1584",
    "indexPrice": "3.1584",
    "fundingRate": "0.00000625",
    "nextFundingTime": 1781388000000
  },
  {
    "symbol": "BREV-USD",
    "openInterest": "0",
    "markPrice": "0",
    "indexPrice": "0",
    "fundingRate": "0.0000125",
    "nextFundingTime": 1767697200000
  },
  {
    "symbol": "BERA-USD",
    "openInterest": "1529.6",
    "markPrice": "0.2598",
    "indexPrice": "0.2607",
    "fundingRate": "-0.0001093644377685",
    "nextFundingTime": 1781388000000
  },
  {
    "symbol": "ONDO-USD",
    "openInterest": "8595.4",
    "markPrice": "0.3638",
    "indexPrice": "0.364",
    "fundingRate": "0.0000125",
    "nextFundingTime": 1781388000000
  },
  {
    "symbol": "TRX-USD",
    "openInterest": "14206",
    "markPrice": "0.31748",
    "indexPrice": "0.31778",
    "fundingRate": "-0.0000211242911583",
    "nextFundingTime": 1781388000000
  },
  {
    "symbol": "MON-USD",
    "openInterest": "974048",
    "markPrice": "0.0215",
    "indexPrice": "0.02152",
    "fundingRate": "-0.0000196389231186",
    "nextFundingTime": 1781388000000
  },
  {
    "symbol": "OP-USD",
    "openInterest": "1711.2",
    "markPrice": "0.10733",
    "indexPrice": "0.1074",
    "fundingRate": "0.0000125",
    "nextFundingTime": 1781388000000
  },
  {
    "symbol": "MU-USD",
    "openInterest": "971.476",
    "markPrice": "992.59",
    "indexPrice": "991.5",
    "fundingRate": "0.00000625",
    "nextFundingTime": 1781388000000
  },
  {
    "symbol": "ORCL-USD",
    "openInterest": "32.746",
    "markPrice": "184.1",
    "indexPrice": "183.51",
    "fundingRate": "0.00000625",
    "nextFundingTime": 1781388000000
  },
  {
    "symbol": "SILVER-USD",
    "openInterest": "440.1",
    "markPrice": "68.055",
    "indexPrice": "68.072",
    "fundingRate": "0.00000625",
    "nextFundingTime": 1781388000000
  },
  {
    "symbol": "FIL-USD",
    "openInterest": "573.4",
    "markPrice": "0.7826",
    "indexPrice": "0.7834",
    "fundingRate": "0.0000125",
    "nextFundingTime": 1781388000000
  },
  {
    "symbol": "ZEC-USD",
    "openInterest": "490.77",
    "markPrice": "422.13",
    "indexPrice": "422.18",
    "fundingRate": "0.0000125",
    "nextFundingTime": 1781388000000
  },
  {
    "symbol": "PENGU-USD",
    "openInterest": "66032",
    "markPrice": "0.006711",
    "indexPrice": "0.006719",
    "fundingRate": "0.0000125",
    "nextFundingTime": 1781388000000
  },
  {
    "symbol": "PLTR-USD",
    "openInterest": "58.378",
    "markPrice": "128.89",
    "indexPrice": "128.67",
    "fundingRate": "0.00000625",
    "nextFundingTime": 1781388000000
  },
  {
    "symbol": "1000SHIB-USD",
    "openInterest": "50206",
    "markPrice": "0.005005",
    "indexPrice": "0.005005",
    "fundingRate": "0.0000125",
    "nextFundingTime": 1781388000000
  },
  {
    "symbol": "CL-USD",
    "openInterest": "24974.312",
    "markPrice": "81.285",
    "indexPrice": "81.264",
    "fundingRate": "0.00000625",
    "nextFundingTime": 1781388000000
  },
  {
    "symbol": "USTECH100-USD",
    "openInterest": "0.2896",
    "markPrice": "29649",
    "indexPrice": "29649",
    "fundingRate": "0.00000625",
    "nextFundingTime": 1781388000000
  },
  {
    "symbol": "APT-USD",
    "openInterest": "2503.52",
    "markPrice": "0.6687",
    "indexPrice": "0.6692",
    "fundingRate": "0.0000125",
    "nextFundingTime": 1781388000000
  },
  {
    "symbol": "XPL-USD",
    "openInterest": "31024",
    "markPrice": "0.0883",
    "indexPrice": "0.0883",
    "fundingRate": "0.0000125",
    "nextFundingTime": 1781388000000
  },
  {
    "symbol": "ETC-USD",
    "openInterest": "45.76",
    "markPrice": "7.169",
    "indexPrice": "7.175",
    "fundingRate": "0.0000125",
    "nextFundingTime": 1781388000000
  },
  {
    "symbol": "SKHX-USD",
    "openInterest": "0.998",
    "markPrice": "1491.8",
    "indexPrice": "1490.8",
    "fundingRate": "0.00000625",
    "nextFundingTime": 1781388000000
  },
  {
    "symbol": "LINK-USD",
    "openInterest": "273.8",
    "markPrice": "7.964",
    "indexPrice": "7.968",
    "fundingRate": "0.0000100187464333",
    "nextFundingTime": 1781388000000
  },
  {
    "symbol": "BASED-USD",
    "openInterest": "7732",
    "markPrice": "0.0695",
    "indexPrice": "0.0695",
    "fundingRate": "0.0000125",
    "nextFundingTime": 1781388000000
  },
  {
    "symbol": "AXS-USD",
    "openInterest": "336",
    "markPrice": "0.9683",
    "indexPrice": "0.9692",
    "fundingRate": "-0.0000199280235658",
    "nextFundingTime": 1781388000000
  },
  {
    "symbol": "CRCL-USD",
    "openInterest": "498.1",
    "markPrice": "79.405",
    "indexPrice": "79.427",
    "fundingRate": "0.00000625",
    "nextFundingTime": 1781388000000
  },
  {
    "symbol": "AVAX-USD",
    "openInterest": "406",
    "markPrice": "6.704",
    "indexPrice": "6.708",
    "fundingRate": "0.0000125",
    "nextFundingTime": 1781388000000
  },
  {
    "symbol": "1000BONK-USD",
    "openInterest": "2471814",
    "markPrice": "0.004491",
    "indexPrice": "0.004496",
    "fundingRate": "0.0000046415566138",
    "nextFundingTime": 1781388000000
  },
  {
    "symbol": "TSM-USD",
    "openInterest": "1.086",
    "markPrice": "424.31",
    "indexPrice": "424.31",
    "fundingRate": "0.00000625",
    "nextFundingTime": 1781388000000
  },
  {
    "symbol": "FARTCOIN-USD",
    "openInterest": "8866.4",
    "markPrice": "0.1202",
    "indexPrice": "0.1202",
    "fundingRate": "0.0000125",
    "nextFundingTime": 1781388000000
  },
  {
    "symbol": "EWY-USD",
    "openInterest": "11.104",
    "markPrice": "197.89",
    "indexPrice": "197.89",
    "fundingRate": "0.00000625",
    "nextFundingTime": 1781388000000
  },
  {
    "symbol": "MSFT-USD",
    "openInterest": "25.43",
    "markPrice": "390.34",
    "indexPrice": "390.09",
    "fundingRate": "0.00000625",
    "nextFundingTime": 1781388000000
  },
  {
    "symbol": "BNB-USD",
    "openInterest": "63.696",
    "markPrice": "608.9",
    "indexPrice": "608.9",
    "fundingRate": "0.0000125",
    "nextFundingTime": 1781388000000
  },
  {
    "symbol": "WLFI-USD",
    "openInterest": "4666",
    "markPrice": "0.05891",
    "indexPrice": "0.05891",
    "fundingRate": "0.0000125",
    "nextFundingTime": 1781388000000
  },
  {
    "symbol": "VIRTUAL-USD",
    "openInterest": "120100",
    "markPrice": "0.641",
    "indexPrice": "0.641",
    "fundingRate": "0.0000125",
    "nextFundingTime": 1781388000000
  },
  {
    "symbol": "TSLA-USD",
    "openInterest": "38.588",
    "markPrice": "406.86",
    "indexPrice": "406.86",
    "fundingRate": "0.00000625",
    "nextFundingTime": 1781388000000
  },
  {
    "symbol": "HYPE-USD",
    "openInterest": "39137.9",
    "markPrice": "60.124",
    "indexPrice": "60.142",
    "fundingRate": "0.0000125",
    "nextFundingTime": 1781388000000
  },
  {
    "symbol": "PUMP-USD",
    "openInterest": "115444",
    "markPrice": "0.001533",
    "indexPrice": "0.001534",
    "fundingRate": "-0.0000152341023778",
    "nextFundingTime": 1781388000000
  },
  {
    "symbol": "XMR-USD",
    "openInterest": "40.932",
    "markPrice": "340.61",
    "indexPrice": "340.24",
    "fundingRate": "0.0000125",
    "nextFundingTime": 1781388000000
  },
  {
    "symbol": "COIN-USD",
    "openInterest": "39.63",
    "markPrice": "161.95",
    "indexPrice": "161.81",
    "fundingRate": "0.00000625",
    "nextFundingTime": 1781388000000
  },
  {
    "symbol": "INTC-USD",
    "openInterest": "77.256",
    "markPrice": "126.265",
    "indexPrice": "126.265",
    "fundingRate": "0.00000625",
    "nextFundingTime": 1781388000000
  },
  {
    "symbol": "HOOD-USD",
    "openInterest": "22.346",
    "markPrice": "93.364",
    "indexPrice": "93.437",
    "fundingRate": "0.00000625",
    "nextFundingTime": 1781388000000
  },
  {
    "symbol": "ADA-USD",
    "openInterest": "3361.6",
    "markPrice": "0.17155",
    "indexPrice": "0.1716",
    "fundingRate": "0.0000125",
    "nextFundingTime": 1781388000000
  },
  {
    "symbol": "SAMSUNG-USD",
    "openInterest": "71.518",
    "markPrice": "220.04",
    "indexPrice": "220",
    "fundingRate": "0.00000625",
    "nextFundingTime": 1781388000000
  },
  {
    "symbol": "ARB-USD",
    "openInterest": "2843.4",
    "markPrice": "0.08531",
    "indexPrice": "0.08537",
    "fundingRate": "-0.0000236420331462",
    "nextFundingTime": 1781388000000
  },
  {
    "symbol": "DOGE-USD",
    "openInterest": "2956",
    "markPrice": "0.08768",
    "indexPrice": "0.08772",
    "fundingRate": "0.0000035023940047",
    "nextFundingTime": 1781388000000
  },
  {
    "symbol": "SPCX-USD",
    "openInterest": "11080.74",
    "markPrice": "165.08",
    "indexPrice": "164.88",
    "fundingRate": "0.00003153544004405",
    "nextFundingTime": 1781388000000
  },
  {
    "symbol": "BCH-USD",
    "openInterest": "4.286",
    "markPrice": "207.15",
    "indexPrice": "207.3",
    "fundingRate": "-0.0000027739198923",
    "nextFundingTime": 1781388000000
  },
  {
    "symbol": "HBAR-USD",
    "openInterest": "3704",
    "markPrice": "0.07812",
    "indexPrice": "0.07816",
    "fundingRate": "0.0000125",
    "nextFundingTime": 1781388000000
  },
  {
    "symbol": "COPPER-USD",
    "openInterest": "591.62",
    "markPrice": "6.5748",
    "indexPrice": "6.5789",
    "fundingRate": "0.00000625",
    "nextFundingTime": 1781388000000
  },
  {
    "symbol": "AMZN-USD",
    "openInterest": "42.64",
    "markPrice": "239.38",
    "indexPrice": "239.4",
    "fundingRate": "0.00000625",
    "nextFundingTime": 1781388000000
  },
  {
    "symbol": "LIT-USD",
    "openInterest": "6779.2",
    "markPrice": "1.6299",
    "indexPrice": "1.6305",
    "fundingRate": "0.0000125",
    "nextFundingTime": 1781388000000
  },
  {
    "symbol": "TON-USD",
    "openInterest": "3059.2",
    "markPrice": "1.7389",
    "indexPrice": "1.742",
    "fundingRate": "-0.0000502030900744",
    "nextFundingTime": 1781388000000
  },
  {
    "symbol": "UNI-USD",
    "openInterest": "325.8",
    "markPrice": "2.5398",
    "indexPrice": "2.541",
    "fundingRate": "0.0000125",
    "nextFundingTime": 1781388000000
  },
  {
    "symbol": "TRUMP-USD",
    "openInterest": "14326.8",
    "markPrice": "2.2105",
    "indexPrice": "2.213",
    "fundingRate": "-0.0000956101271573",
    "nextFundingTime": 1781388000000
  },
  {
    "symbol": "ENA-USD",
    "openInterest": "11580",
    "markPrice": "0.0845",
    "indexPrice": "0.0846",
    "fundingRate": "0.0000125",
    "nextFundingTime": 1781388000000
  },
  {
    "symbol": "SNDK-USD",
    "openInterest": "583.12",
    "markPrice": "1995.83",
    "indexPrice": "1996.26",
    "fundingRate": "0.00000625",
    "nextFundingTime": 1781388000000
  },
  {
    "symbol": "NVDA-USD",
    "openInterest": "79.18",
    "markPrice": "205.25",
    "indexPrice": "205.25",
    "fundingRate": "0.00000625",
    "nextFundingTime": 1781388000000
  },
  {
    "symbol": "ETH-USD",
    "openInterest": "7602.3608",
    "markPrice": "1675.9",
    "indexPrice": "1676.7",
    "fundingRate": "0.0000037922275767",
    "nextFundingTime": 1781388000000
  },
  {
    "symbol": "LTC-USD",
    "openInterest": "52.98",
    "markPrice": "43.89",
    "indexPrice": "43.92",
    "fundingRate": "0.0000125",
    "nextFundingTime": 1781388000000
  },
  {
    "symbol": "US500-USD",
    "openInterest": "0.344",
    "markPrice": "7443.2",
    "indexPrice": "7444",
    "fundingRate": "0.00000625",
    "nextFundingTime": 1781388000000
  },
  {
    "symbol": "ASTER-USD",
    "openInterest": "652",
    "markPrice": "0.6395",
    "indexPrice": "0.6394",
    "fundingRate": "0.0000125",
    "nextFundingTime": 1781388000000
  },
  {
    "symbol": "GOOGL-USD",
    "openInterest": "86.832",
    "markPrice": "361.67",
    "indexPrice": "361.25",
    "fundingRate": "0.00000625",
    "nextFundingTime": 1781388000000
  },
  {
    "symbol": "CHZ-USD",
    "openInterest": "327824",
    "markPrice": "0.02526",
    "indexPrice": "0.0253",
    "fundingRate": "-0.0000012078599416",
    "nextFundingTime": 1781388000000
  },
  {
    "symbol": "BTC-USD",
    "openInterest": "220.11198",
    "markPrice": "64246",
    "indexPrice": "64275",
    "fundingRate": "0.0000017703958971",
    "nextFundingTime": 1781388000000
  },
  {
    "symbol": "AMD-USD",
    "openInterest": "9.128",
    "markPrice": "512.85",
    "indexPrice": "513.04",
    "fundingRate": "0.00000625",
    "nextFundingTime": 1781388000000
  },
  {
    "symbol": "MSTR-USD",
    "openInterest": "379.722",
    "markPrice": "126.21",
    "indexPrice": "126.21",
    "fundingRate": "0.00000625",
    "nextFundingTime": 1781388000000
  },
  {
    "symbol": "SOL-USD",
    "openInterest": "59591.79",
    "markPrice": "68.36",
    "indexPrice": "68.4",
    "fundingRate": "-0.0000091907213545",
    "nextFundingTime": 1781388000000
  },
  {
    "symbol": "XLM-USD",
    "openInterest": "55974",
    "markPrice": "0.18671",
    "indexPrice": "0.1869",
    "fundingRate": "-0.0000415727114674",
    "nextFundingTime": 1781388000000
  }
]